MANIFEST.in
README.rst
setup.cfg
setup.py
django_js_utils/__init__.py
django_js_utils/conf_jsutils.py
django_js_utils/models.py
django_js_utils/utils.py
django_js_utils/management/__init__.py
django_js_utils/management/commands/__init__.py
django_js_utils/management/commands/js_urls.py
django_js_utils/static/js/dutils.js
django_js_utils_ng.egg-info/PKG-INFO
django_js_utils_ng.egg-info/SOURCES.txt
django_js_utils_ng.egg-info/dependency_links.txt
django_js_utils_ng.egg-info/requires.txt
django_js_utils_ng.egg-info/top_level.txt